mcthings/__init__.py
mcthings/_version.py
mcthings/block.py
mcthings/blocks.py
mcthings/blocks_gallery.py
mcthings/blocks_memory.py
mcthings/bridge.py
mcthings/building.py
mcthings/circle.py
mcthings/collage.py
mcthings/fence.py
mcthings/house.py
mcthings/line.py
mcthings/platform.py
mcthings/pyramid.py
mcthings/river.py
mcthings/scene.py
mcthings/schematic.py
mcthings/server.py
mcthings/sphere.py
mcthings/thing.py
mcthings/town.py
mcthings/utils.py
mcthings/vox.py
mcthings/wall.py
mcthings/wool.py
mcthings/world.py
mcthings/decorators/__init__.py
mcthings/decorators/border_decorator.py
mcthings/decorators/decorator.py
mcthings/decorators/light_decorator.py
mcthings/renderers/__init__.py
mcthings/renderers/raspberry_pi.py
mcthings/renderers/renderer.py
mcthings-0.60.0.data/scripts/vox2schematic
mcthings-0.60.0.dist-info/LICENSE
mcthings-0.60.0.dist-info/METADATA
mcthings-0.60.0.dist-info/WHEEL
mcthings-0.60.0.dist-info/top_level.txt
mcthings-0.60.0.dist-info/RECORD
